desed/__init__.py
desed/download.py
desed/generate_synthetic.py
desed/logger.py
desed/post_process.py
desed/soundscape.py
desed/utils.py
desed-1.3.8.dist-info/LICENSE
desed-1.3.8.dist-info/METADATA
desed-1.3.8.dist-info/WHEEL
desed-1.3.8.dist-info/top_level.txt
desed-1.3.8.dist-info/RECORD
