Metadata-Version: 2.1
Name: desed
Version: 1.3.8
Summary: DESED dataset utils
Home-page: https://github.com/turpaultn/DESED
Author: Nicolas Turpault
Author-email: turpaultn@gmail.com
License: MIT
License-File: LICENSE
Requires-Dist: scaper >=1.6.5rc0
Requires-Dist: numpy >=1.15.4
Requires-Dist: pandas >=0.24.0
Requires-Dist: dcase-util >=0.2.11
Requires-Dist: yt-dlp >=2022.3.8.2
Requires-Dist: soundfile >=0.10.1
Requires-Dist: jams >=0.3.4
Requires-Dist: tqdm >=4.29.1
Requires-Dist: requests >=2.21.0
Requires-Dist: resampy >=0.4.3
